{"taxon":{"species":"ferdinandi","subspecies":"","author":"O. Pickard-Cambridge, 1870","taxonRank":"species","status":"VALID","genus":"Miagrammopes","genusObject":{"genus":"Miagrammopes","author":"O. Pickard-Cambridge, 1870","genLsid":"urn:lsid:nmbe.ch:spidergen:03360"},"family":"Uloboridae","familyObject":{"family":"Uloboridae","author":"Thorell, 1869","famLsid":"urn:lsid:nmbe.ch:spiderfam:0098"},"distribution":"Sri Lanka","lsid":"urn:lsid:nmbe.ch:spidersp:006256","referenceObject":{"reference":"Pickard-Cambridge, O. (1870a). Descriptions and sketches of two new species of Araneida, with characters of a new genus. Journal of the Linnean Society of London, Zoology 10(47): 398-405, pl. 14.","doi":"10.1111\/j.1096-3642.1870.tb00669.x","pageDescription":"404"}}}