{"taxon":{"species":"brignolii","subspecies":"","author":"Thaler \u0026 Steinberger, 1988","taxonRank":"species","status":"VALID","genus":"Carniella","genusObject":{"genus":"Carniella","author":"Thaler \u0026 Steinberger, 1988","genLsid":"urn:lsid:nmbe.ch:spidergen:00670"},"family":"Theridiidae","familyObject":{"family":"Theridiidae","author":"Sundevall, 1833","famLsid":"urn:lsid:nmbe.ch:spiderfam:0099"},"distribution":"Belgium, Switzerland, Germany, Austria, Czechia, Romania","lsid":"urn:lsid:nmbe.ch:spidersp:007193","referenceObject":{"reference":"Thaler, K. \u0026 Steinberger, K.-H. (1988). Zwei neue Zwerg-Kugelspinnen aus \u00d6sterreich (Arachnida: Aranei, Theridiidae). Revue Suisse de Zoologie 95(4): 997-1004.","doi":"10.5962\/bhl.part.81946","pageDescription":"998"}}}