{"taxon":{"species":"meridionalis","subspecies":"","author":"(Costa, 1835)","taxonRank":"species","status":"VALID","genus":"Nemesia","genusObject":{"genus":"Nemesia","author":"Audouin, 1826","genLsid":"urn:lsid:nmbe.ch:spidergen:00125"},"family":"Nemesiidae","familyObject":{"family":"Nemesiidae","author":"Simon, 1889","famLsid":"urn:lsid:nmbe.ch:spiderfam:0007"},"distribution":"Spain, France, Italy, Algeria?","lsid":"urn:lsid:nmbe.ch:spidersp:001228","referenceObject":{"reference":"Costa, O. G. (1835). Fauna del regno di Napoli. Aracnidi. Napoli, (Araneae, pp. 14-24, pls. 1, 2).","doi":"10.5962\/bhl.title.135337","pageDescription":"14"}}}