{"taxon":{"species":"sinensis","subspecies":"","author":"Pocock, 1901","taxonRank":"species","status":"VALID","genus":"Nemesia","genusObject":{"genus":"Nemesia","author":"Audouin, 1826","genLsid":"urn:lsid:nmbe.ch:spidergen:00125"},"family":"Nemesiidae","familyObject":{"family":"Nemesiidae","author":"Simon, 1889","famLsid":"urn:lsid:nmbe.ch:spiderfam:0007"},"distribution":"China","lsid":"urn:lsid:nmbe.ch:spidersp:001236","referenceObject":{"reference":"Pocock, R. I. (1901e). On some new trap-door spiders from China. Proceedings of the Zoological Society of London 70(2): 207-215, pl. 21.","doi":"10.1111\/j.1469-7998.1901.tb08540.x","pageDescription":"212"}}}