{"taxon":{"species":"amazonicus","subspecies":"","author":"(Levi, 1995)","taxonRank":"species","status":"SYNONYM","genus":"Spintharidius","genusObject":{"genus":"Spintharidius","author":"Simon, 1893","genLsid":"urn:lsid:nmbe.ch:spidergen:01563"},"family":"Araneidae","familyObject":{"family":"Araneidae","author":"Clerck, 1757","famLsid":"urn:lsid:nmbe.ch:spiderfam:0102"},"distribution":null,"lsid":"urn:lsid:nmbe.ch:spidersp:016306","referenceObject":{"reference":"","doi":"","pageDescription":""}},"validTaxon":{"_href":"https:\/\/wsc.nmbe.ch\/api\/lsid\/urn:lsid:nmbe.ch:spidersp:017072"}}