{"taxon":{"species":"solitudus","subspecies":"","author":"Tanasevitch, 1994","taxonRank":"species","status":"VALID","genus":"Stemonyphantes","genusObject":{"genus":"Stemonyphantes","author":"Menge, 1866","genLsid":"urn:lsid:nmbe.ch:spidergen:01280"},"family":"Linyphiidae","familyObject":{"family":"Linyphiidae","author":"Blackwall, 1859","famLsid":"urn:lsid:nmbe.ch:spiderfam:0103"},"distribution":"Turkmenistan","lsid":"urn:lsid:nmbe.ch:spidersp:012763","referenceObject":{"reference":"Tanasevitch, A. V. (1994). A new species of the spider genus Stemonyphantes Menge from Turkmenistan (Aranei Linyphiidae Stemonyphantinae). Arthropoda Selecta 3(1-2): 49-50.","doi":"","pageDescription":"49"}}}