{"taxon":{"species":"molicola","subspecies":"","author":"(Strand, 1906)","taxonRank":"species","status":"VALID","genus":"Allocosa","genusObject":{"genus":"Allocosa","author":"Banks, 1900","genLsid":"urn:lsid:nmbe.ch:spidergen:01588"},"family":"Lycosidae","familyObject":{"family":"Lycosidae","author":"Sundevall, 1833","famLsid":"urn:lsid:nmbe.ch:spiderfam:0100"},"distribution":"Ethiopia","lsid":"urn:lsid:nmbe.ch:spidersp:017301","referenceObject":{"reference":"Strand, E. (1906b). Diagnosen nordafrikanischer, haupts\u00e4chlich von Carlo Freiherr von Erlanger gesammelter Spinnen. Zoologischer Anzeiger 30: 604-637, 655-690.","doi":"","pageDescription":"685"}}}