{"taxon":{"species":"prima","subspecies":"","author":"(Millidge, 1991)","taxonRank":"species","status":"VALID","genus":"Agyneta","genusObject":{"genus":"Agyneta","author":"Hull, 1911","genLsid":"urn:lsid:nmbe.ch:spidergen:00822"},"family":"Linyphiidae","familyObject":{"family":"Linyphiidae","author":"Blackwall, 1859","famLsid":"urn:lsid:nmbe.ch:spiderfam:0103"},"distribution":"Colombia","lsid":"urn:lsid:nmbe.ch:spidersp:011696","referenceObject":{"reference":"Millidge, A. F. (1991). Further linyphiid spiders (Araneae) from South America. Bulletin of the American Museum of Natural History 205: 1-199.","doi":"","pageDescription":"95"}}}