{"taxon":{"species":"myrrhea","subspecies":"","author":"(Simon, 1895)","taxonRank":"species","status":"VALID","genus":"Singa","genusObject":{"genus":"Singa","author":"C. L. Koch, 1836","genLsid":"urn:lsid:nmbe.ch:spidergen:01559"},"family":"Araneidae","familyObject":{"family":"Araneidae","author":"Clerck, 1757","famLsid":"urn:lsid:nmbe.ch:spiderfam:0102"},"distribution":"India","lsid":"urn:lsid:nmbe.ch:spidersp:017056","referenceObject":{"reference":"Simon, E. (1895a). Histoire naturelle des araign\u00e9es. Deuxi\u00e8me \u00e9dition, tome premier. Roret, Paris, pp. 761-1084.","doi":"10.5962\/bhl.title.51973","pageDescription":"824"}}}