{"taxon":{"species":"bithynica","subspecies":"","author":"Kulczy\u0144ski, 1903","taxonRank":"species","status":"VALID","genus":"Gnaphosa","genusObject":{"genus":"Gnaphosa","author":"Latreille, 1804","genLsid":"urn:lsid:nmbe.ch:spidergen:02428"},"family":"Gnaphosidae","familyObject":{"family":"Gnaphosidae","author":"Banks, 1892","famLsid":"urn:lsid:nmbe.ch:spiderfam:0054"},"distribution":"Greece (Crete), Turkey, Lebanon, Israel, Iran","lsid":"urn:lsid:nmbe.ch:spidersp:027201","referenceObject":{"reference":"Kulczy\u0144ski, W. (1903b). Arachnoidea in Asia Minore et ad Constantinopolim a Dre F. Werner collecta. Sitzungsberichte der Kaiserlichen Akademie der Wissenschaften, Mathematisch-naturwissenschaftliche Klasse, Wien 112: 627-680, 1 pl.","doi":"","pageDescription":"641"}}}