{"taxon":{"species":"psammodromus","subspecies":"","author":"Simon, 1910","taxonRank":"species","status":"VALID","genus":"Ammoxenus","genusObject":{"genus":"Ammoxenus","author":"Simon, 1893","genLsid":"urn:lsid:nmbe.ch:spidergen:02327"},"family":"Gnaphosidae","familyObject":{"family":"Gnaphosidae","author":"Banks, 1892","famLsid":"urn:lsid:nmbe.ch:spiderfam:0054"},"distribution":"Namibia, Botswana, South Africa","lsid":"urn:lsid:nmbe.ch:spidersp:026161","referenceObject":{"reference":"Simon, E. (1910b). Arachnoidea: Araneae (II.). In: Schultze, L. (ed.) Zoologische und anthropologische Ergebnisse einer Forschungsreise im westlichen und zentralen S\u00fcdafrika. Vierter Band. Systematik und Tiergeographie. Denkschriften der Medizinisch-Naturwissenschaftlichen Gesellschaft zu Jena 16: 175-218.","doi":"","pageDescription":"189"}}}