{"taxon":{"species":"javanus","subspecies":"","author":"Pocock, 1897","taxonRank":"species","status":"VALID","genus":"Ctenus","genusObject":{"genus":"Ctenus","author":"Walckenaer, 1805","genLsid":"urn:lsid:nmbe.ch:spidergen:01785"},"family":"Ctenidae","familyObject":{"family":"Ctenidae","author":"Keyserling, 1877","famLsid":"urn:lsid:nmbe.ch:spiderfam:0036"},"distribution":"Indonesia (Java)","lsid":"urn:lsid:nmbe.ch:spidersp:020601","referenceObject":{"reference":"Pocock, R. I. (1897c). Spinnen (Araneae). In: K\u00fckenthal, W. (ed.) Ergebnisse einer zoologische Forschungsreise in dem Molukken und Borneo. Abhandlungen der Senckenbergischen Naturforschenden Gesellschaft 23: 591-629.","doi":"","pageDescription":"610"}}}