{"taxon":{"species":"major","subspecies":"","author":"Simon, 1896","taxonRank":"species","status":"VALID","genus":"Oedignatha","genusObject":{"genus":"Oedignatha","author":"Thorell, 1881","genLsid":"urn:lsid:nmbe.ch:spidergen:02254"},"family":"Liocranidae","familyObject":{"family":"Liocranidae","author":"Simon, 1897","famLsid":"urn:lsid:nmbe.ch:spiderfam:0047"},"distribution":"Sri Lanka","lsid":"urn:lsid:nmbe.ch:spidersp:025389","referenceObject":{"reference":"Simon, E. (1896b). Descriptions d\u0027arachnides nouveaux de la famille des Clubionidae. Annales de la Soci\u00e9t\u00e9 Entomologique de Belgique 40(9): 400-422.","doi":"","pageDescription":"415"}}}