{"taxon":{"species":"deletrix","subspecies":"","author":"O. Pickard-Cambridge, 1885","taxonRank":"species","status":"VALID","genus":"Clubiona","genusObject":{"genus":"Clubiona","author":"Latreille, 1804","genLsid":"urn:lsid:nmbe.ch:spidergen:02215"},"family":"Clubionidae","familyObject":{"family":"Clubionidae","author":"Wagner, 1887","famLsid":"urn:lsid:nmbe.ch:spiderfam:0048"},"distribution":"India, China?, Taiwan?, Japan?","lsid":"urn:lsid:nmbe.ch:spidersp:024518","referenceObject":{"reference":"Pickard-Cambridge, O. (1885b). Araneidea. In: Scientific results of the second Yarkand mission; based upon the collections and notes of the late Ferdinand Stoliczka, Ph. D. Government of India, Calcutta, 115 pp., 2 pls.","doi":"10.5962\/bhl.title.119960","pageDescription":"21"}}}