{"taxon":{"species":"dixiensis","subspecies":"","author":"Chamberlin, 1925","taxonRank":"species","status":"VALID","genus":"Wadotes","genusObject":{"genus":"Wadotes","author":"Chamberlin, 1925","genLsid":"urn:lsid:nmbe.ch:spidergen:02056"},"family":"Agelenidae","familyObject":{"family":"Agelenidae","author":"C. L. Koch, 1837","famLsid":"urn:lsid:nmbe.ch:spiderfam:0037"},"distribution":"USA","lsid":"urn:lsid:nmbe.ch:spidersp:023100","referenceObject":{"reference":"Chamberlin, R. V. (1925b). Notes on North American spiders heretofore referred to Coelotes. Proceedings of the Biological Society of Washington 38: 119-124.","doi":"","pageDescription":"120"}}}