{"taxon":{"species":"rostrata","subspecies":"","author":"Paik, 1985","taxonRank":"species","status":"VALID","genus":"Clubiona","genusObject":{"genus":"Clubiona","author":"Latreille, 1804","genLsid":"urn:lsid:nmbe.ch:spidergen:02215"},"family":"Clubionidae","familyObject":{"family":"Clubionidae","author":"Wagner, 1887","famLsid":"urn:lsid:nmbe.ch:spiderfam:0048"},"distribution":"Russia (Far East), China, Korea, Japan","lsid":"urn:lsid:nmbe.ch:spidersp:024752","referenceObject":{"reference":"Paik, K. Y. (1985b). Three new species of clubionid spiders from Korea. Korean Arachnology 1(1): 1-11.","doi":"","pageDescription":"3"}}}