{"taxon":{"species":"limpidus","subspecies":"","author":"Galiano, 1980","taxonRank":"species","status":"VALID","genus":"Lyssomanes","genusObject":{"genus":"Lyssomanes","author":"Hentz, 1845","genLsid":"urn:lsid:nmbe.ch:spidergen:03038"},"family":"Salticidae","familyObject":{"family":"Salticidae","author":"Blackwall, 1841","famLsid":"urn:lsid:nmbe.ch:spiderfam:0101"},"distribution":"Colombia","lsid":"urn:lsid:nmbe.ch:spidersp:034319","referenceObject":{"reference":"Galiano, M. E. (1980a). Revisi\u00f3n del g\u00e9nero Lyssomanes Hentz, 1845 (Araneae, Salticidae). Opera Lilloana 30: 1-104.","doi":"","pageDescription":"72"}}}