{"taxon":{"species":"delmasi","subspecies":"","author":"Berland, 1927","taxonRank":"species","status":"VALID","genus":"Misumenops","genusObject":{"genus":"Misumenops","author":"F. O. Pickard-Cambridge, 1900","genLsid":"urn:lsid:nmbe.ch:spidergen:02702"},"family":"Thomisidae","familyObject":{"family":"Thomisidae","author":"Sundevall, 1833","famLsid":"urn:lsid:nmbe.ch:spiderfam:0058"},"distribution":"Marquesas Is.","lsid":"urn:lsid:nmbe.ch:spidersp:030649","referenceObject":{"reference":"Berland, L. (1927a). Note sur les araign\u00e9es recueillies aux Iles Marquises par le R. P. Sim\u00e9on Delmas. Bulletin du Mus\u00e9um National d\u0027Histoire Naturelle de Paris 33: 366-368.","doi":"","pageDescription":"368"}}}