{"taxon":{"species":"laniger","subspecies":"","author":"Logunov \u0026 Marusik, 2000","taxonRank":"species","status":"VALID","genus":"Aelurillus","genusObject":{"genus":"Aelurillus","author":"Simon, 1885","genLsid":"urn:lsid:nmbe.ch:spidergen:02796"},"family":"Salticidae","familyObject":{"family":"Salticidae","author":"Blackwall, 1841","famLsid":"urn:lsid:nmbe.ch:spiderfam:0101"},"distribution":"North Macedonia, Kazakhstan","lsid":"urn:lsid:nmbe.ch:spidersp:032187","referenceObject":{"reference":"Logunov, D. V. \u0026 Marusik, Y. M. (2000). Miscellaneous notes on Palaearctic Salticidae (Arachnida: Aranei). Arthropoda Selecta 8(4, 1999): 263-292.","doi":"","pageDescription":"265"}}}