{"taxon":{"species":"biseratensis","subspecies":"","author":"Badcock, 1918","taxonRank":"species","status":"VALID","genus":"Myrmarachne","genusObject":{"genus":"Myrmarachne","author":"MacLeay, 1839","genLsid":"urn:lsid:nmbe.ch:spidergen:03086"},"family":"Salticidae","familyObject":{"family":"Salticidae","author":"Blackwall, 1841","famLsid":"urn:lsid:nmbe.ch:spiderfam:0101"},"distribution":"Malaysia, Indonesia (Borneo)","lsid":"urn:lsid:nmbe.ch:spidersp:034741","referenceObject":{"reference":"Badcock, H. D. (1918). Ant-like spiders from Malaya collected by the Annandale-Robinson Expedition 1901-02. Proceedings of the Zoological Society of London 87(3\/4, 1917): 277-321.","doi":"10.1111\/j.1096-3642.1917.tb02070.x","pageDescription":"312"}}}