{"taxon":{"species":"marmoratus","subspecies":"","author":"Kulczy\u0144ski, 1891","taxonRank":"species","status":"VALID","genus":"Philodromus","genusObject":{"genus":"Philodromus","author":"Walckenaer, 1826","genLsid":"urn:lsid:nmbe.ch:spidergen:02615"},"family":"Philodromidae","familyObject":{"family":"Philodromidae","author":"Thorell, 1870","famLsid":"urn:lsid:nmbe.ch:spiderfam:0057"},"distribution":"Austria, Czechia to Bulgaria, Ukraine","lsid":"urn:lsid:nmbe.ch:spidersp:038325","referenceObject":{"reference":"Chyzer, C. \u0026 Kulczy\u0144ski, W. (1891). Araneae Hungariae. Tomus I. Academia Scientarum Hungaricae, Budapest, 170 pp., 4 Pls.","doi":"","pageDescription":"111"}}}