{"taxon":{"species":"soesilae","subspecies":"","author":"Makhan, 2006","taxonRank":"species","status":"VALID","genus":"Chirothecia","genusObject":{"genus":"Chirothecia","author":"Taczanowski, 1878","genLsid":"urn:lsid:nmbe.ch:spidergen:02888"},"family":"Salticidae","familyObject":{"family":"Salticidae","author":"Blackwall, 1841","famLsid":"urn:lsid:nmbe.ch:spiderfam:0101"},"distribution":"Suriname","lsid":"urn:lsid:nmbe.ch:spidersp:042341","referenceObject":{"reference":"Makhan, D. (2006b). Peckhamia soesilae sp. nov. and Chirothecia soesilae sp. nov. from Suriname (Araneae: Salticidae). Calodema 6: 29-33.","doi":"","pageDescription":"30"}}}