{"taxon":{"species":"linnaei","subspecies":"","author":"Rix, 2008","taxonRank":"species","status":"VALID","genus":"Micropholcomma","genusObject":{"genus":"Micropholcomma","author":"Crosby \u0026 Bishop, 1927","genLsid":"urn:lsid:nmbe.ch:spidergen:00596"},"family":"Anapidae","familyObject":{"family":"Anapidae","author":"Simon, 1895","famLsid":"urn:lsid:nmbe.ch:spiderfam:0030"},"distribution":"Australia (Western Australia)","lsid":"urn:lsid:nmbe.ch:spidersp:042068","referenceObject":{"reference":"Rix, M. G. (2008). A new species of Micropholcomma (Araneae: Araneoidea: Micropholcommatidae) from Western Australia. Records of the Western Australian Museum 24: 343-348.","doi":"","pageDescription":"343"}}}