{"taxon":{"species":"amchickeringi","subspecies":"","author":"Levi, 2005","taxonRank":"species","status":"VALID","genus":"Mangora","genusObject":{"genus":"Mangora","author":"O. Pickard-Cambridge, 1889","genLsid":"urn:lsid:nmbe.ch:spidergen:01510"},"family":"Araneidae","familyObject":{"family":"Araneidae","author":"Clerck, 1757","famLsid":"urn:lsid:nmbe.ch:spiderfam:0102"},"distribution":"Panama, Colombia, Venezuela, Trinidad","lsid":"urn:lsid:nmbe.ch:spidersp:040023","referenceObject":{"reference":"Levi, H. W. (2005a). The orb-weaver genus Mangora of Mexico, Central America, and the West Indies (Araneae: Araneidae). Bulletin of the Museum of Comparative Zoology 158: 139-182.","doi":"","pageDescription":"160"}}}