{"taxon":{"species":"inflatus","subspecies":"","author":"Bayer, 2012","taxonRank":"species","status":"VALID","genus":"Psechrus","genusObject":{"genus":"Psechrus","author":"Thorell, 1878","genLsid":"urn:lsid:nmbe.ch:spidergen:01772"},"family":"Psechridae","familyObject":{"family":"Psechridae","author":"Simon, 1890","famLsid":"urn:lsid:nmbe.ch:spiderfam:0087"},"distribution":"India, China","lsid":"urn:lsid:nmbe.ch:spidersp:045123","referenceObject":{"reference":"Bayer, S. (2012). The lace-sheet-weavers \u2013 a long story (Araneae: Psechridae: Psechrus). Zootaxa 3379: 1-170.","doi":"10.11646\/zootaxa.3379.1.1","pageDescription":"72"}}}