{"taxon":{"species":"mammillanus","subspecies":"","author":"O. Pickard-Cambridge, 1875","taxonRank":"species","status":"SYNONYM","genus":"Liphistius","genusObject":{"genus":"Liphistius","author":"Schi\u00f8dte, 1849","genLsid":"urn:lsid:nmbe.ch:spidergen:00002"},"family":"Liphistiidae","familyObject":{"family":"Liphistiidae","author":"Thorell, 1869","famLsid":"urn:lsid:nmbe.ch:spiderfam:0001"},"distribution":"Malaysia","lsid":"urn:lsid:nmbe.ch:spidersp:049933","referenceObject":{"reference":"","doi":"","pageDescription":""}},"validTaxon":{"_href":"https:\/\/wsc.nmbe.ch\/api\/lsid\/urn:lsid:nmbe.ch:spidersp:000037"}}