{"taxon":{"species":"helios","subspecies":"","author":"Tanikawa \u0026 Miyashita, 2014","taxonRank":"species","status":"VALID","genus":"Heptathela","genusObject":{"genus":"Heptathela","author":"Kishida, 1923","genLsid":"urn:lsid:nmbe.ch:spidergen:00001"},"family":"Liphistiidae","familyObject":{"family":"Liphistiidae","author":"Thorell, 1869","famLsid":"urn:lsid:nmbe.ch:spiderfam:0001"},"distribution":"Japan (Ryukyu Is.)","lsid":"urn:lsid:nmbe.ch:spidersp:047369","referenceObject":{"reference":"Tanikawa, A. \u0026 Miyashita, T. (2014). Discovery of a cryptic species of Heptathela from the northernmost part of Okinawajima Is., Southwest Japan, as revealed by mitochondrial and nuclear DNA. Acta Arachnologica 63(2): 65-72.","doi":"10.2476\/asjaa.63.65","pageDescription":"68"}}}