{"taxon":{"species":"yunchuni","subspecies":"","author":"Zhao \u0026 Li, 2018","taxonRank":"species","status":"VALID","genus":"Pinelema","genusObject":{"genus":"Pinelema","author":"Wang \u0026 Li, 2012","genLsid":"urn:lsid:nmbe.ch:spidergen:04046"},"family":"Telemidae","familyObject":{"family":"Telemidae","author":"Fage, 1913","famLsid":"urn:lsid:nmbe.ch:spiderfam:0092"},"distribution":"China","lsid":"urn:lsid:nmbe.ch:spidersp:050568","referenceObject":{"reference":"Zhao, H. F., Yao, Z. Y., Song, Y. \u0026 Li, S. Q. (2018b). Taxonomic study of the Pinelema bailongensis species group with descriptions of six new species from China (Araneae, Telemidae). ZooKeys 784: 7-57.","doi":"10.3897\/zookeys.784.27758","pageDescription":"46"}}}