{"taxon":{"species":"crassiventre","subspecies":"","author":"Strand, 1913","taxonRank":"species","status":"NOMEN_DUBIUM","genus":"Gonatium","genusObject":{"genus":"Gonatium","author":"Menge, 1868","genLsid":"urn:lsid:nmbe.ch:spidergen:00991"},"family":"Linyphiidae","familyObject":{"family":"Linyphiidae","author":"Blackwall, 1859","famLsid":"urn:lsid:nmbe.ch:spiderfam:0103"},"distribution":null,"lsid":"urn:lsid:nmbe.ch:spidersp:051114","referenceObject":{"reference":"","doi":"","pageDescription":""}}}