{"taxon":{"species":"culicinus","subspecies":"","author":"(Simon, 1893)","taxonRank":"species","status":"VALID","genus":"Modisimus","genusObject":{"genus":"Modisimus","author":"Simon, 1893","genLsid":"urn:lsid:nmbe.ch:spidergen:00401"},"family":"Pholcidae","familyObject":{"family":"Pholcidae","author":"C. L. Koch, 1850","famLsid":"urn:lsid:nmbe.ch:spiderfam:0017"},"distribution":"South America. Introduced to Germany, Czechia, Zaire, Seychelles, Sri Lanka, Indonesia, China, Australia, Pacific Is.","lsid":"urn:lsid:nmbe.ch:spidersp:003594","referenceObject":{"reference":"Simon, E. (1893a). Histoire naturelle des araign\u00e9es. Deuxi\u00e8me \u00e9dition, tome premier. Roret, Paris, pp. 257-488.","doi":"10.5962\/bhl.title.51973","pageDescription":"486"}}}