{"taxon":{"species":"stenaspis","subspecies":"","author":"Simon, 1892","taxonRank":"species","status":"VALID","genus":"Triaeris","genusObject":{"genus":"Triaeris","author":"Simon, 1892","genLsid":"urn:lsid:nmbe.ch:spidergen:00549"},"family":"Oonopidae","familyObject":{"family":"Oonopidae","author":"Simon, 1890","famLsid":"urn:lsid:nmbe.ch:spiderfam:0083"},"distribution":"Africa. Introduced to North, Central, South America, Caribbean, Europe, Iran, Taiwan, Australia, Pacific Is.","lsid":"urn:lsid:nmbe.ch:spidersp:005213","referenceObject":{"reference":"Simon, E. (1892e). On the spiders of the island of St. Vincent. Part 1. Proceedings of the Zoological Society of London 59(4, 1891): 549-575, pl. 42.","doi":"","pageDescription":"561"}}}