{"taxon":{"species":"biharicus","subspecies":"","author":"(Gravely, 1915)","taxonRank":"species","status":"VALID","genus":"Heligmomerus","genusObject":{"genus":"Heligmomerus","author":"Simon, 1892","genLsid":"urn:lsid:nmbe.ch:spidergen:00082"},"family":"Idiopidae","familyObject":{"family":"Idiopidae","author":"Simon, 1889","famLsid":"urn:lsid:nmbe.ch:spiderfam:0012"},"distribution":"India","lsid":"urn:lsid:nmbe.ch:spidersp:000720","referenceObject":{"reference":"Gravely, F. H. (1915). Notes on Indian mygalomorph spiders. Records of the Indian Museum, Calcutta 11: 257-287.","doi":"","pageDescription":"261"}}}