{"taxon":{"species":"davidi","subspecies":"","author":"Simon, 1884","taxonRank":"species","status":"VALID","genus":"Segestria","genusObject":{"genus":"Segestria","author":"Latreille, 1804","genLsid":"urn:lsid:nmbe.ch:spidergen:00479"},"family":"Segestriidae","familyObject":{"family":"Segestriidae","author":"Simon, 1893","famLsid":"urn:lsid:nmbe.ch:spiderfam:0089"},"distribution":"Syria","lsid":"urn:lsid:nmbe.ch:spidersp:004308","referenceObject":{"reference":"Simon, E. (1884i). Etudes arachnologiques. 15e M\u00e9moire. XXII. Arachnides recueillis par M. l\u0027abb\u00e9 David \u00e0 Smyrne, \u00e0 Beirouth et \u00e0 Akb\u00e8s en 1883. Annales de la Soci\u00e9t\u00e9 Entomologique de France (6) 4(3): 181-196.","doi":"","pageDescription":"190"}}}