{"taxon":{"species":"mollicoma","subspecies":"","author":"(Ausserer, 1875)","taxonRank":"species","status":"SYNONYM","genus":"Grammostola","genusObject":{"genus":"Grammostola","author":"Simon, 1892","genLsid":"urn:lsid:nmbe.ch:spidergen:00224"},"family":"Theraphosidae","familyObject":{"family":"Theraphosidae","author":"Thorell, 1869","famLsid":"urn:lsid:nmbe.ch:spiderfam:0010"},"distribution":null,"lsid":"urn:lsid:nmbe.ch:spidersp:002020","referenceObject":{"reference":"","doi":"","pageDescription":""}},"validTaxon":{"_href":"https:\/\/wsc.nmbe.ch\/api\/lsid\/urn:lsid:nmbe.ch:spidersp:001789"}}