{"taxon":{"species":"colemani","subspecies":"","author":"Raven, 1986","taxonRank":"species","status":"VALID","genus":"Sason","genusObject":{"genus":"Sason","author":"Simon, 1887","genLsid":"urn:lsid:nmbe.ch:spidergen:00177"},"family":"Barychelidae","familyObject":{"family":"Barychelidae","author":"Simon, 1889","famLsid":"urn:lsid:nmbe.ch:spiderfam:0009"},"distribution":"Australia (Queensland)","lsid":"urn:lsid:nmbe.ch:spidersp:001558","referenceObject":{"reference":"Raven, R. J. (1986). A revision of the spider genus Sason Simon (Sasoninae, Barychelidae, Mygalomorphae) and its historical biogeography. Journal of Arachnology 14: 47-70.","doi":"","pageDescription":"56"}}}