{"taxon":{"species":"philippinus","subspecies":"","author":"(Schmidt, 1999)","taxonRank":"species","status":"VALID","genus":"Orphnaecus","genusObject":{"genus":"Orphnaecus","author":"Simon, 1892","genLsid":"urn:lsid:nmbe.ch:spidergen:00258"},"family":"Theraphosidae","familyObject":{"family":"Theraphosidae","author":"Thorell, 1869","famLsid":"urn:lsid:nmbe.ch:spiderfam:0010"},"distribution":"Philippines","lsid":"urn:lsid:nmbe.ch:spidersp:002404","referenceObject":{"reference":"Schmidt, G. (1999b). Selenobrachys philippinus gen. et sp. n. (Araneae: Theraphosidae: Selenocosmiinae), eine neue Theraphosidae sp. von der Insel Negros (Philippinen). Arachnologisches Magazin 7(5\/6): 1-13.","doi":"","pageDescription":"4"}}}