{"taxon":{"species":"furcifera","subspecies":"","author":"(O. Pickard-Cambridge, 1881)","taxonRank":"species","status":"VALID","genus":"Hypognatha","genusObject":{"genus":"Hypognatha","author":"Gu\u00e9rin, 1839","genLsid":"urn:lsid:nmbe.ch:spidergen:01493"},"family":"Araneidae","familyObject":{"family":"Araneidae","author":"Clerck, 1757","famLsid":"urn:lsid:nmbe.ch:spiderfam:0102"},"distribution":"Brazil","lsid":"urn:lsid:nmbe.ch:spidersp:016153","referenceObject":{"reference":"Pickard-Cambridge, O. (1881d). On some new genera and species of Araneidea. Proceedings of the Zoological Society of London 49(3): 765-775, Pl. LXVI.","doi":"10.1111\/j.1096-3642.1881.tb01333.x","pageDescription":"771"}}}