{"taxon":{"species":"alpicola","subspecies":"","author":"(Simon, 1876)","taxonRank":"species","status":"VALID","genus":"Alopecosa","genusObject":{"genus":"Alopecosa","author":"Simon, 1885","genLsid":"urn:lsid:nmbe.ch:spidergen:01589"},"family":"Lycosidae","familyObject":{"family":"Lycosidae","author":"Sundevall, 1833","famLsid":"urn:lsid:nmbe.ch:spiderfam:0100"},"distribution":"Spain, France, Italy, Russia (Europe), China, Caucasus?, Kazakhstan?","lsid":"urn:lsid:nmbe.ch:spidersp:017379","referenceObject":{"reference":"Simon, E. (1876a). Les arachnides de France. Tome troisi\u00e8me. Roret, Paris, 364 pp., pl. IX-XIII.","doi":"","pageDescription":"263"}}}