{"taxon":{"species":"anuncinatus","subspecies":"ochrorufus","author":"Franganillo, 1931","taxonRank":"subspecies","status":"NOMEN_DUBIUM","genus":"Araneus","genusObject":{"genus":"Araneus","author":"Clerck, 1757","genLsid":"urn:lsid:nmbe.ch:spidergen:01440"},"family":"Araneidae","familyObject":{"family":"Araneidae","author":"Clerck, 1757","famLsid":"urn:lsid:nmbe.ch:spiderfam:0102"},"distribution":null,"lsid":"urn:lsid:nmbe.ch:spidersp:014708","referenceObject":{"reference":"","doi":"","pageDescription":""}}}