{"taxon":{"species":"rhomboidea","subspecies":"comorensis","author":"Strand, 1916","taxonRank":"subspecies","status":"VALID","genus":"Gasteracantha","genusObject":{"genus":"Gasteracantha","author":"Sundevall, 1833","genLsid":"urn:lsid:nmbe.ch:spidergen:01484"},"family":"Araneidae","familyObject":{"family":"Araneidae","author":"Clerck, 1757","famLsid":"urn:lsid:nmbe.ch:spiderfam:0102"},"distribution":"Comoros, Mayotte","lsid":"urn:lsid:nmbe.ch:spidersp:016050","referenceObject":{"reference":"Strand, E. (1916d). Arachnologica varia, I-IX. Archiv f\u00fcr Naturgeschichte 81(A11): 112-123.","doi":"","pageDescription":"117"}}}