{"taxon":{"species":"mongolensis","subspecies":"","author":"Eskov \u0026 Marusik, 1992","taxonRank":"species","status":"VALID","genus":"Silometopoides","genusObject":{"genus":"Silometopoides","author":"Eskov, 1990","genLsid":"urn:lsid:nmbe.ch:spidergen:01257"},"family":"Linyphiidae","familyObject":{"family":"Linyphiidae","author":"Blackwall, 1859","famLsid":"urn:lsid:nmbe.ch:spiderfam:0103"},"distribution":"Russia (South Siberia), Mongolia","lsid":"urn:lsid:nmbe.ch:spidersp:012618","referenceObject":{"reference":"Eskov, K. Y. \u0026 Marusik, Y. M. (1992d). On the Siberio-Nearctic erigonine spider genus Silometopoides (Araneida: Linyphiidae). Reichenbachia 29: 97-103.","doi":"","pageDescription":"99"}}}