{"taxon":{"species":"mexicana","subspecies":"","author":"(O. Pickard-Cambridge, 1896)","taxonRank":"species","status":"VALID","genus":"Goeldia","genusObject":{"genus":"Goeldia","author":"Keyserling, 1891","genLsid":"urn:lsid:nmbe.ch:spidergen:02074"},"family":"Titanoecidae","familyObject":{"family":"Titanoecidae","author":"Lehtinen, 1967","famLsid":"urn:lsid:nmbe.ch:spiderfam:0094"},"distribution":"Mexico","lsid":"urn:lsid:nmbe.ch:spidersp:023178","referenceObject":{"reference":"Pickard-Cambridge, O. (1896a). Arachnida. Araneida. In: Biologia Centrali-Americana, Zoology. London 1, 161-224.","doi":"","pageDescription":"170"}}}