{"taxon":{"species":"radleyi","subspecies":"","author":"(Simon, 1898)","taxonRank":"species","status":"VALID","genus":"Alistra","genusObject":{"genus":"Alistra","author":"Thorell, 1894","genLsid":"urn:lsid:nmbe.ch:spidergen:01930"},"family":"Hahniidae","familyObject":{"family":"Hahniidae","author":"Bertkau, 1878","famLsid":"urn:lsid:nmbe.ch:spiderfam:0041"},"distribution":"Sri Lanka","lsid":"urn:lsid:nmbe.ch:spidersp:021840","referenceObject":{"reference":"Simon, E. (1898a). Histoire naturelle des araign\u00e9es. Deuxi\u00e8me \u00e9dition, tome second. Roret, Paris, pp. 193-380.","doi":"10.5962\/bhl.title.51973","pageDescription":"276"}}}