{"taxon":{"species":"patalongensis","subspecies":"","author":"Simon, 1901","taxonRank":"species","status":"VALID","genus":"Oxyopes","genusObject":{"genus":"Oxyopes","author":"Latreille, 1804","genLsid":"urn:lsid:nmbe.ch:spidergen:01747"},"family":"Oxyopidae","familyObject":{"family":"Oxyopidae","author":"Thorell, 1869","famLsid":"urn:lsid:nmbe.ch:spiderfam:0084"},"distribution":"Malaysia","lsid":"urn:lsid:nmbe.ch:spidersp:020075","referenceObject":{"reference":"Simon, E. (1901k). On the Arachnida collected during the Skeat expedition to the Malay Peninsula. Proceedings of the Zoological Society of London 71(1): 45-84.","doi":"10.1111\/j.1469-7998.1901.tb08164.x","pageDescription":"70"}}}