{"taxon":{"species":"giersbergi","subspecies":"","author":"Kraus, 1955","taxonRank":"species","status":"VALID","genus":"Liocranum","genusObject":{"genus":"Liocranum","author":"L. Koch, 1866","genLsid":"urn:lsid:nmbe.ch:spidergen:02187"},"family":"Liocranidae","familyObject":{"family":"Liocranidae","author":"Simon, 1897","famLsid":"urn:lsid:nmbe.ch:spiderfam:0047"},"distribution":"Italy (Sardinia)","lsid":"urn:lsid:nmbe.ch:spidersp:024235","referenceObject":{"reference":"Kraus, O. (1955a). Spinnen von Korsika, Sardinien und Elba (Arach., Araneae). Senckenbergiana Biologica 36: 371-394.","doi":"","pageDescription":"382"}}}