{"taxon":{"species":"apscheronica","subspecies":"","author":"Dunin, 1984","taxonRank":"species","status":"VALID","genus":"Berlandina","genusObject":{"genus":"Berlandina","author":"Dalmas, 1922","genLsid":"urn:lsid:nmbe.ch:spidergen:02405"},"family":"Gnaphosidae","familyObject":{"family":"Gnaphosidae","author":"Banks, 1892","famLsid":"urn:lsid:nmbe.ch:spiderfam:0054"},"distribution":"Russia (Europe), Azerbaijan, Kazakhstan","lsid":"urn:lsid:nmbe.ch:spidersp:026680","referenceObject":{"reference":"Dunin, P. M. (1984a). [Fauna and ecology of the spiders of the Apscheron Peninsula, Azerbadjan SSR]. In: Fauna and Ecology of Arachnids. University of Perm, pp. 45-60.","doi":"","pageDescription":"49"}}}