{"taxon":{"species":"spuridens","subspecies":"","author":"Strand, 1907","taxonRank":"species","status":"NOMEN_DUBIUM","genus":"Rhene","genusObject":{"genus":"Rhene","author":"Thorell, 1869","genLsid":"urn:lsid:nmbe.ch:spidergen:03194"},"family":"Salticidae","familyObject":{"family":"Salticidae","author":"Blackwall, 1841","famLsid":"urn:lsid:nmbe.ch:spiderfam:0101"},"distribution":"Indonesia (Java)","lsid":"urn:lsid:nmbe.ch:spidersp:035925","referenceObject":{"reference":"Strand, E. (1907m). Spinnen des Zoologischen Instituts in T\u00fcbingen. Zoologische Jahrb\u00fccher, Abteilung f\u00fcr Systematik, Geographie und Biologie der Tiere 24: 391-468.","doi":"","pageDescription":"451"}}}