{"taxon":{"species":"scarabaeoides","subspecies":"","author":"(O. Pickard-Cambridge, 1894)","taxonRank":"species","status":"VALID","genus":"Cylistella","genusObject":{"genus":"Cylistella","author":"Simon, 1901","genLsid":"urn:lsid:nmbe.ch:spidergen:02910"},"family":"Salticidae","familyObject":{"family":"Salticidae","author":"Blackwall, 1841","famLsid":"urn:lsid:nmbe.ch:spiderfam:0101"},"distribution":"Mexico, Panama","lsid":"urn:lsid:nmbe.ch:spidersp:033017","referenceObject":{"reference":"Pickard-Cambridge, O. (1894a). Arachnida. Araneida. In: Biologia Centrali-Americana, Zoology. London 1, 121-144.","doi":"","pageDescription":"121"}}}