{"taxon":{"species":"tsurui","subspecies":"","author":"Ono, 2007","taxonRank":"species","status":"VALID","genus":"Carniella","genusObject":{"genus":"Carniella","author":"Thaler \u0026 Steinberger, 1988","genLsid":"urn:lsid:nmbe.ch:spidergen:00670"},"family":"Theridiidae","familyObject":{"family":"Theridiidae","author":"Sundevall, 1833","famLsid":"urn:lsid:nmbe.ch:spiderfam:0099"},"distribution":"Taiwan","lsid":"urn:lsid:nmbe.ch:spidersp:039804","referenceObject":{"reference":"Ono, H., Chang, Y. H. \u0026 Tso, I. M. (2007). Three new spiders of the families Theridiidae and Anapidae (Araneae) from southern Taiwan. Memoirs of the National Science Museum Tokyo 44: 71-82.","doi":"","pageDescription":"72"}}}