{"taxon":{"species":"kochi","subspecies":"","author":"(\u017babka, 1987)","taxonRank":"species","status":"VALID","genus":"Maratus","genusObject":{"genus":"Maratus","author":"Karsch, 1878","genLsid":"urn:lsid:nmbe.ch:spidergen:03055"},"family":"Salticidae","familyObject":{"family":"Salticidae","author":"Blackwall, 1841","famLsid":"urn:lsid:nmbe.ch:spiderfam:0101"},"distribution":"Australia","lsid":"urn:lsid:nmbe.ch:spidersp:034275","referenceObject":{"reference":"\u017babka, M. (1987b). Salticidae (Araneae) of Oriental, Australian and Pacific Regions, II. Genera Lycidas and Maratus. Annales Zoologici, Warszawa 40: 451-482.","doi":"","pageDescription":"460"}}}