{"taxon":{"species":"riojanensis","subspecies":"","author":"Galiano, 1965","taxonRank":"species","status":"VALID","genus":"Helvetia","genusObject":{"genus":"Helvetia","author":"G. W. Peckham \u0026 E. G. Peckham, 1894","genLsid":"urn:lsid:nmbe.ch:spidergen:02985"},"family":"Salticidae","familyObject":{"family":"Salticidae","author":"Blackwall, 1841","famLsid":"urn:lsid:nmbe.ch:spiderfam:0101"},"distribution":"Argentina","lsid":"urn:lsid:nmbe.ch:spidersp:033879","referenceObject":{"reference":"Galiano, M. E. (1965d). Descripcion de Helvetia riojanensis sp. n. y del alotipo m de H. albovittata Simon (Araneae, Salticidae). Revista de la Sociedad Entomol\u00f3gica Argentina 27: 47-50.","doi":"","pageDescription":"47"}}}