{"taxon":{"species":"quadrispinus","subspecies":"","author":"Caporiacco, 1933","taxonRank":"species","status":"VALID","genus":"Xysticus","genusObject":{"genus":"Xysticus","author":"C. L. Koch, 1835","genLsid":"urn:lsid:nmbe.ch:spidergen:02786"},"family":"Thomisidae","familyObject":{"family":"Thomisidae","author":"Sundevall, 1833","famLsid":"urn:lsid:nmbe.ch:spiderfam:0058"},"distribution":"Libya","lsid":"urn:lsid:nmbe.ch:spidersp:032042","referenceObject":{"reference":"Caporiacco, L. di (1933). Araneidi. In: Spedizione scientifica all\u0027oasi di Cufra (Marzo-Luglio 1931). Annali del Museo Civico di Storia Naturale di Genova 56: 311-340.","doi":"","pageDescription":"326"}}}