{"taxon":{"species":"griswoldi","subspecies":"","author":"Engelbrecht \u0026 Prendini, 2012","taxonRank":"species","status":"VALID","genus":"Stasimopus","genusObject":{"genus":"Stasimopus","author":"Simon, 1892","genLsid":"urn:lsid:nmbe.ch:spidergen:00070"},"family":"Stasimopidae","familyObject":{"family":"Stasimopidae","author":"Bond, Opatova \u0026 Hedin, 2020","famLsid":"urn:lsid:nmbe.ch:spiderfam:0138"},"distribution":"South Africa","lsid":"urn:lsid:nmbe.ch:spidersp:044634","referenceObject":{"reference":"Engelbrecht, I. \u0026 Prendini, L. (2012). Cryptic diversity of South African trapdoor spiders: three new species of Stasimopus Simon, 1892 (Mygalomorphae, Ctenizidae), and redescription of Stasimopus robertsi Hewitt, 1910. American Museum Novitates 3732: 1-42.","doi":"10.1206\/3732.2","pageDescription":"27"}}}