{"taxon":{"species":"larisae","subspecies":"","author":"Logunov, 2017","taxonRank":"species","status":"VALID","genus":"Synagelides","genusObject":{"genus":"Synagelides","author":"Strand, 1906","genLsid":"urn:lsid:nmbe.ch:spidergen:03247"},"family":"Salticidae","familyObject":{"family":"Salticidae","author":"Blackwall, 1841","famLsid":"urn:lsid:nmbe.ch:spiderfam:0101"},"distribution":"Indonesia (Sumatra)","lsid":"urn:lsid:nmbe.ch:spidersp:049818","referenceObject":{"reference":"Logunov, D. V. (2017). New species and records in the genus Synagelides Strand in B\u00f6senberg et Strand, 1906 (Aranei: Salticidae) from the Oriental region. Arthropoda Selecta 26(4): 315-322.","doi":"10.15298\/arthsel.26.4.06","pageDescription":"318"}}}