{"taxon":{"species":"algarve","subspecies":"","author":"Decae, 2010","taxonRank":"species","status":"VALID","genus":"Ummidia","genusObject":{"genus":"Ummidia","author":"Thorell, 1875","genLsid":"urn:lsid:nmbe.ch:spidergen:00071"},"family":"Halonoproctidae","familyObject":{"family":"Halonoproctidae","author":"Pocock, 1901","famLsid":"urn:lsid:nmbe.ch:spiderfam:0130"},"distribution":"Portugal","lsid":"urn:lsid:nmbe.ch:spidersp:043497","referenceObject":{"reference":"Decae, A. E. (2010). The genus Ummidia Thorell 1875 in the western Mediterranean, a review (Araneae: Mygalomorphae: Ctenizidae). Journal of Arachnology 38(2): 328-340.","doi":"10.1636\/A09-85.1","pageDescription":"329"}}}