{"taxon":{"species":"murata","subspecies":"","author":"Framenau \u0026 Baehr, 2007","taxonRank":"species","status":"VALID","genus":"Dingosa","genusObject":{"genus":"Dingosa","author":"Roewer, 1955","genLsid":"urn:lsid:nmbe.ch:spidergen:01610"},"family":"Lycosidae","familyObject":{"family":"Lycosidae","author":"Sundevall, 1833","famLsid":"urn:lsid:nmbe.ch:spiderfam:0100"},"distribution":"Southern Australia","lsid":"urn:lsid:nmbe.ch:spidersp:041055","referenceObject":{"reference":"Framenau, V. W. \u0026 Baehr, B. C. (2007). Revision of the Australian wolf spider genus Dingosa Roewer, 1955 (Araneae, Lycosidae). Journal of Natural History 41(25-28): 1603-1629.","doi":"10.1080\/00222930701475717","pageDescription":"1618"}}}