{"taxon":{"species":"tangara","subspecies":"","author":"Marsh, Baehr, Glatz \u0026 Framenau, 2018","taxonRank":"species","status":"VALID","genus":"Ariadna","genusObject":{"genus":"Ariadna","author":"Audouin, 1826","genLsid":"urn:lsid:nmbe.ch:spidergen:00477"},"family":"Segestriidae","familyObject":{"family":"Segestriidae","author":"Simon, 1893","famLsid":"urn:lsid:nmbe.ch:spiderfam:0089"},"distribution":"Australia (South Australia)","lsid":"urn:lsid:nmbe.ch:spidersp:050668","referenceObject":{"reference":"Marsh, J. R., Baehr, B. C., Glatz, R. V. \u0026 Framenau, V. W. (2018). New species of tube web spiders of the genus Ariadna from South Australia (Araneae, Segestriidae). Evolutionary Systematics 2: 137-149.","doi":"10.3897\/evolsyst.2.29172","pageDescription":"142"}}}