{"taxon":{"species":"daweiensis","subspecies":"","author":"Sivayyapram \u0026 Warrit, 2020","taxonRank":"species","status":"VALID","genus":"Phlogiellus","genusObject":{"genus":"Phlogiellus","author":"Pocock, 1897","genLsid":"urn:lsid:nmbe.ch:spidergen:00263"},"family":"Theraphosidae","familyObject":{"family":"Theraphosidae","author":"Thorell, 1869","famLsid":"urn:lsid:nmbe.ch:spiderfam:0010"},"distribution":"Myanmar","lsid":"urn:lsid:nmbe.ch:spidersp:052394","referenceObject":{"reference":"Sivayyapram, V., Kunsete, C., Songsangchote, C., Thanoosing, C., Traiyasut, P. \u0026 Warrit, N. (2020). Two new species of the Southeast Asian dwarf tarantula genus Phlogiellus Pocock, 1887 (Theraphosidae, Selenocosmiinae) and a discussion on the taxonomic problem of the genus. Zootaxa 4859(4): 487-506, 4869(4): 599-600.","doi":"10.11646\/zootaxa.4859.4.2","pageDescription":"490"}}}