{"taxon":{"species":"heliophaniformis","subspecies":"","author":"D\u00f6nitz \u0026 Strand, 1906","taxonRank":"species","status":"VALID","genus":"Euophrys","genusObject":{"genus":"Euophrys","author":"C. L. Koch, 1834","genLsid":"urn:lsid:nmbe.ch:spidergen:02946"},"family":"Salticidae","familyObject":{"family":"Salticidae","author":"Blackwall, 1841","famLsid":"urn:lsid:nmbe.ch:spiderfam:0101"},"distribution":"Japan","lsid":"urn:lsid:nmbe.ch:spidersp:050760","referenceObject":{"reference":"B\u00f6senberg, W. \u0026 Strand, E. (1906). Japanische Spinnen. Abhandlungen der Senckenbergischen Naturforschenden Gesellschaft 30: 93-422.","doi":"","pageDescription":"393"}}}