{"taxon":{"species":"juno","subspecies":"","author":"Bellvert \u0026 Arnedo, 2021","taxonRank":"species","status":"VALID","genus":"Theridion","genusObject":{"genus":"Theridion","author":"Walckenaer, 1805","genLsid":"urn:lsid:nmbe.ch:spidergen:00725"},"family":"Theridiidae","familyObject":{"family":"Theridiidae","author":"Sundevall, 1833","famLsid":"urn:lsid:nmbe.ch:spiderfam:0099"},"distribution":"USA (Hawaii)","lsid":"urn:lsid:nmbe.ch:spidersp:052729","referenceObject":{"reference":"Bellvert, A., Gillespie, R. \u0026 Arnedo, M. A. (2021). A happy family: systematic revision of the endemic Theridion spiders (Araneae, Theridiidae) of the Hawaiian Islands. Invertebrate Systematics 35(1): 1-58.","doi":"10.1071\/IS20001","pageDescription":"20"}}}